easy_text_clustering/__init__.py
easy_text_clustering/clusterer.py
easy_text_clustering/optimizer.py
easy_text_clustering-1.3.5.dist-info/METADATA
easy_text_clustering-1.3.5.dist-info/WHEEL
easy_text_clustering-1.3.5.dist-info/licenses/LICENSE
easy_text_clustering-1.3.5.dist-info/RECORD
