Metadata-Version: 2.3
Name: easy_text_clustering
Version: 1.3.5
Summary: User-friendly, low-code text clustering
Project-URL: Homepage, https://github.com/billingsmoore/easy_text_clustering
Project-URL: Issues, https://github.com/billingsmoore/easy_text_clustering/issues
Author-email: billingsmoore <billingsmoore@gmail.com>
Classifier: License :: OSI Approved :: Apache Software License
Classifier: Operating System :: OS Independent
Classifier: Programming Language :: Python :: 3
Requires-Python: >=3.8
Requires-Dist: datasets
Requires-Dist: faiss-cpu
Requires-Dist: huggingface-hub
Requires-Dist: matplotlib
Requires-Dist: numpy
Requires-Dist: optuna
Requires-Dist: pandas
Requires-Dist: plotly
Requires-Dist: scikit-learn
Requires-Dist: seaborn
Requires-Dist: sentence-transformers
Requires-Dist: tqdm
Requires-Dist: umap-learn
